Metadata-Version: 2.1
Name: odoo11-addon-mis-builder-budget
Version: 11.0.3.5.0
Summary: Create budgets for MIS reports
Home-page: https://github.com/OCA/mis-builder/
Author: ACSONE SA/NV, Odoo Community Association (OCA)
Author-email: support@odoo-community.org
License: AGPL-3
Platform: UNKNOWN
Classifier: Programming Language :: Python
Classifier: Framework :: Odoo
Classifier: License :: OSI Approved :: GNU Affero General Public License v3
Classifier: Development Status :: 5 - Production/Stable
Requires-Python: >=2.7, !=3.0.*, !=3.1.*, !=3.2.*, !=3.3.*, !=3.4.*
Requires-Dist: odoo11-addon-mis-builder
Requires-Dist: odoo (<11.1dev,>=11.0a)
